Metadata-Version: 1.0
Name: Json-Handling
Version: 1.1.0
Summary: Nothing fancy really, basic Json handler
Home-page: https://github.com/LordMartron94/JSON_Handling/tree/master/json_storage_handling
Author: Matthew David van der Hoorn
Author-email: m.david.vanderhoorn@gmail.com
License: UNKNOWN
Platform: UNKNOWN
